build/lib/geotz/__init__.py
build/lib/geotz/geolookup.py
build/lib/geotz/tzlookup.py
build/lib/geotz/data/__init__.py
geotz/__init__.py
geotz/geolookup.py
geotz/tzlookup.py
geotz/data/__init__.py
geotz/data/geonames_all_countries_sorted.tsv
geotz-0.0.2a4.dist-info/LICENSE
geotz-0.0.2a4.dist-info/METADATA
geotz-0.0.2a4.dist-info/WHEEL
geotz-0.0.2a4.dist-info/top_level.txt
geotz-0.0.2a4.dist-info/RECORD
