Metadata-Version: 2.1
Name: geotz
Version: 0.0.2a4
Summary: Simple library for offline lookup of the timezone for a location.
License: ## License for included geographic data
Project-URL: Source, https://github.com/dmayo3/geotz
Project-URL: Docs, http://geotz.readthedocs.io/
Keywords: geo,timezones,tz
Classifier: Development Status :: 3 - Alpha
Classifier: Natural Language :: English
Classifier: Operating System :: OS Independent
Classifier: Intended Audience :: Developers
Classifier: Programming Language :: Python
Classifier: Programming Language :: Python :: 3
Classifier: Programming Language :: Python :: 3.8
Classifier: Programming Language :: Python :: 3.9
Classifier: Programming Language :: Python :: 3.10
Classifier: Programming Language :: Python :: 3.11
Classifier: Programming Language :: Python :: 3.12
Classifier: Programming Language :: Python :: 3.13
Classifier: Programming Language :: Python :: 3.14
Classifier: Programming Language :: Python :: 3 :: Only
Classifier: Programming Language :: Python :: Implementation :: CPython
Classifier: Topic :: Software Development :: Libraries
Classifier: Topic :: Utilities
Classifier: Typing :: Typed
Requires-Python: >=3.9
License-File: LICENSE
Requires-Dist: tzfpy ~=0.15
Provides-Extra: docs
Requires-Dist: sphinx-rtd-theme >=1.2.0 ; extra == 'docs'
Provides-Extra: pytz
Requires-Dist: tzfpy[pytz] ~=0.15 ; extra == 'pytz'
